firestart_utils/__init__.py
firestart_utils/logger/__init__.py
firestart_utils/logger/logger.py
firestart_utils/utils/__init__.py
firestart_utils/utils/utils.py
firestart_utils-0.2.6.dist-info/METADATA
firestart_utils-0.2.6.dist-info/WHEEL
firestart_utils-0.2.6.dist-info/RECORD
