Metadata-Version: 2.3
Name: firestart-utils
Version: 0.2.6
Summary: 
Author: Çağdaş Öztürk
Author-email: cagdas@littlerocket.nl
Requires-Python: >=3.11,<4.0
Classifier: Programming Language :: Python :: 3
Classifier: Programming Language :: Python :: 3.11
Classifier: Programming Language :: Python :: 3.12
Classifier: Programming Language :: Python :: 3.13
Requires-Dist: requests (>=2,<3)
